[
  {
    "ContainingType": "SalesDatePrediction.API.Controllers.CustomersController",
    "Method": "GetPredictions",
    "RelativePath": "api/Customers/predictions",
    "HttpMethod": "GET",
    "IsController": true,
    "Order": 0,
    "Parameters": [
      {
        "Name": "nameFilter",
        "Type": "System.String",
        "IsRequired": false
      }
    ],
    "ReturnTypes": [
      {
        "Type": "System.Collections.Generic.IEnumerable\u00601[[SalesDatePrediction.Core.Application.DTOs.CustomerPredictionDto, SalesDatePrediction.Core, Version=1.0.0.0, Culture=neutral, PublicKeyToken=null]]",
        "MediaTypes": [
          "text/plain",
          "application/json",
          "text/json"
        ],
        "StatusCode": 200
      }
    ]
  },
  {
    "ContainingType": "SalesDatePrediction.API.Controllers.EmployeesController",
    "Method": "GetAll",
    "RelativePath": "api/Employees",
    "HttpMethod": "GET",
    "IsController": true,
    "Order": 0,
    "Parameters": [],
    "ReturnTypes": [
      {
        "Type": "System.Collections.Generic.IEnumerable\u00601[[SalesDatePrediction.Core.Application.DTOs.EmployeeDto, SalesDatePrediction.Core, Version=1.0.0.0, Culture=neutral, PublicKeyToken=null]]",
        "MediaTypes": [
          "text/plain",
          "application/json",
          "text/json"
        ],
        "StatusCode": 200
      }
    ]
  },
  {
    "ContainingType": "SalesDatePrediction.API.Controllers.OrdersController",
    "Method": "CreateOrder",
    "RelativePath": "api/Orders",
    "HttpMethod": "POST",
    "IsController": true,
    "Order": 0,
    "Parameters": [
      {
        "Name": "orderDto",
        "Type": "SalesDatePrediction.Core.Application.DTOs.CreateOrderDto",
        "IsRequired": true
      }
    ],
    "ReturnTypes": []
  },
  {
    "ContainingType": "SalesDatePrediction.API.Controllers.OrdersController",
    "Method": "GetCustomerOrders",
    "RelativePath": "api/Orders/customer/{customerId}",
    "HttpMethod": "GET",
    "IsController": true,
    "Order": 0,
    "Parameters": [
      {
        "Name": "customerId",
        "Type": "System.String",
        "IsRequired": true
      }
    ],
    "ReturnTypes": [
      {
        "Type": "System.Collections.Generic.IEnumerable\u00601[[SalesDatePrediction.Core.Application.DTOs.OrderDto, SalesDatePrediction.Core, Version=1.0.0.0, Culture=neutral, PublicKeyToken=null]]",
        "MediaTypes": [
          "text/plain",
          "application/json",
          "text/json"
        ],
        "StatusCode": 200
      }
    ]
  },
  {
    "ContainingType": "SalesDatePrediction.API.Controllers.ProductsController",
    "Method": "GetAll",
    "RelativePath": "api/Products",
    "HttpMethod": "GET",
    "IsController": true,
    "Order": 0,
    "Parameters": [],
    "ReturnTypes": [
      {
        "Type": "System.Collections.Generic.IEnumerable\u00601[[SalesDatePrediction.Core.Application.DTOs.ProductDto, SalesDatePrediction.Core, Version=1.0.0.0, Culture=neutral, PublicKeyToken=null]]",
        "MediaTypes": [
          "text/plain",
          "application/json",
          "text/json"
        ],
        "StatusCode": 200
      }
    ]
  },
  {
    "ContainingType": "SalesDatePrediction.API.Controllers.ShippersController",
    "Method": "GetAll",
    "RelativePath": "api/Shippers",
    "HttpMethod": "GET",
    "IsController": true,
    "Order": 0,
    "Parameters": [],
    "ReturnTypes": [
      {
        "Type": "System.Collections.Generic.IEnumerable\u00601[[SalesDatePrediction.Core.Application.DTOs.ShipperDto, SalesDatePrediction.Core, Version=1.0.0.0, Culture=neutral, PublicKeyToken=null]]",
        "MediaTypes": [
          "text/plain",
          "application/json",
          "text/json"
        ],
        "StatusCode": 200
      }
    ]
  }
]